{
  "id": "SVS_EVENT_PRIORITY",
  "name": "Priorizar SvS",
  "domain": "events",
  "priority": "high",
  "conditions": [
    { "field": "profile.objective", "op": "eq", "value": "svs" },
    { "field": "currentEvents", "op": "contains", "value": "SvS" }
  ],
  "recommendation": "SvS é seu objetivo principal e está ativo agora. Direcione recursos e aceleradores para ele.",
  "explanation": "Alinhar o objetivo declarado do jogador com o evento ativo evita dispersão de recursos em eventos secundários.",
  "impact": "high",
  "confidence": 0.8
}
